README.rst
setup.py
src/justbases_gui/__init__.py
src/justbases_gui/_config.py
src/justbases_gui/_frame.py
src/justbases_gui/_version.py
src/justbases_gui.egg-info/PKG-INFO
src/justbases_gui.egg-info/SOURCES.txt
src/justbases_gui.egg-info/dependency_links.txt
src/justbases_gui.egg-info/requires.txt
src/justbases_gui.egg-info/top_level.txt